CompArch labs/Copy of bcd_to_gray_df.v
module bcd_to_gray_df(a,b,c,d,e,f,g,h);
	input a,b,c,d;
	output e,f,g,h;
	
	assign e=a|1,
		f=a^b,
		g=b^c,
		h=c^d;
endmodule

CompArch labs/tb_bcd_to_gray.v
`include "bcd_to_gray_df.v"

module tb_bcd_to_gray;
	reg a,b,c,d;
	wire e,f,g,h;
	bcd_to_gray_df bcd_to_gray_gate (a,b,c,d,e,f,g,h);
	initial
		begin
			$monitor(,$time," bcd = %b%b%b%b grey = %b%b%b%b",a,b,c,d,e,f,g,h);
			#00 a=1'b0;b=1'b0;c=1'b0;d=1'b0;
			#10 a=1'b0;b=1'b0;c=1'b0;d=1'b1;
			#20 a=1'b0;b=1'b0;c=1'b1;d=1'b0;
			#30 a=1'b0;b=1'b0;c=1'b1;d=1'b1;
			#40 a=1'b0;b=1'b1;c=1'b0;d=1'b0;
			#50 a=1'b0;b=1'b1;c=1'b0;d=1'b1;
			#60 a=1'b0;b=1'b1;c=1'b1;d=1'b0;
			#70 a=1'b0;b=1'b1;c=1'b1;d=1'b1;
			#80 a=1'b1;b=1'b0;c=1'b0;d=1'b0;
			#90 a=1'b1;b=1'b0;c=1'b0;d=1'b1;
			#100 $finish;
		end
		
	initial
		begin
			$dumpfile("bcd_to_gray_testbench.vcd");
			$dumpvars;
		end

endmodule

CompArch labs/bcd_to_gray_testbench.vcd
$date
	Tue Aug 22 15:44:13 2017
$end
$version
	Icarus Verilog
$end
$timescale
	1s
$end
$scope module tb_bcd_to_gray $end
$var wire 1 ! h $end
$var wire 1 " g $end
$var wire 1 # f $end
$var wire 1 $ e $end
$var reg 1 % a $end
$var reg 1 & b $end
$var reg 1 ' c $end
$var reg 1 ( d $end
$scope module bcd_to_gray_gate $end
$var wire 1 % a $end
$var wire 1 & b $end
$var wire 1 ' c $end
$var wire 1 ( d $end
$var wire 1 # f $end
$var wire 1 " g $end
$var wire 1 ! h $end
$var wire 1 $ e $end
$upscope $end
$upscope $end
$enddefinitions $end
#0
$dumpvars
0(
0'
0&
0%
1$
0#
0"
0!
$end
#10
1!
1(
#30
1"
0(
1'
#60
0!
1(
#100
1#
0(
0'
1&
#150
1!
1(
#210
0"
0(
1'
#280
0!
1(
#360
0(
0'
0&
1%
#450
1!
1(
